ethio_date_converter/__init__.py
ethio_date_converter/converter.py
tests/__init__.py
tests/test_converter.py
ethio_date_converter-0.1.5.dist-info/METADATA
ethio_date_converter-0.1.5.dist-info/WHEEL
ethio_date_converter-0.1.5.dist-info/top_level.txt
ethio_date_converter-0.1.5.dist-info/RECORD
