Metadata-Version: 2.1
Name: ethio-date-converter
Version: 0.1.5
Summary: Ethiopian date converter.
Home-page: https://github.com/Yasusync/ethiopian_date_converter
License: GNU General Public License (GPL), Version 3
Classifier: Development Status :: 4 - Beta
Classifier: Intended Audience :: Developers
Classifier: License :: OSI Approved :: GNU General Public License (GPL)
Classifier: Programming Language :: Python :: 3
Provides: ethiopian_date
Requires-Dist: six>=1.11.0
